ciaos/__init__.py
ciaos/client.py
ciaos/config.py
ciaos/test.py
ciaos/util/__init__.py
ciaos/util/flatbuffer/FileData.py
ciaos/util/flatbuffer/FileDataList.py
ciaos/util/flatbuffer/__init__.py
ciaos/util/flatbuffer/flatbuffer_handler.py
ciaos-1.0.0.dist-info/METADATA
ciaos-1.0.0.dist-info/WHEEL
ciaos-1.0.0.dist-info/top_level.txt
ciaos-1.0.0.dist-info/RECORD
