Metadata-Version: 2.1
Name: ciaos
Version: 1.0.0
Author: cialabs
Requires-Dist: flatbuffers
Requires-Dist: requests
